{
  "version": "5.3.1",
  "flags": {},
  "shapes": [
    {
      "label": "other",
      "points": [
        [
          1001.8867924528302,
          220.2830188679245
        ],
        [
          969.8113207547169,
          250.47169811320754
        ],
        [
          1005.6603773584906,
          287.73584905660374
        ],
        [
          1037.7358490566037,
          251.88679245283018
        ]
      ],
      "group_id": null,
      "description": "",
      "shape_type": "polygon",
      "flags": {}
    }
  ],
  "imagePath": "00051.jpg",
  "imageHeight": 800,
  "imageWidth": 1360
}