{
  "version": "5.3.1",
  "flags": {},
  "shapes": [
    {
      "label": "other",
      "points": [
        [
          942.2818791946308,
          341.61073825503354
        ],
        [
          957.8523489932886,
          373.5570469798658
        ],
        [
          973.6912751677852,
          340.2684563758389
        ]
      ],
      "group_id": null,
      "description": "",
      "shape_type": "polygon",
      "flags": {}
    },
    {
      "label": "mandatory",
      "points": [
        [
          953.9597315436241,
          375.3020134228188
        ],
        [
          950.0671140939597,
          379.5973154362416
        ],
        [
          947.3825503355705,
          386.1744966442953
        ],
        [
          948.4563758389262,
          393.8255033557047
        ],
        [
          951.9463087248322,
          397.58389261744964
        ],
        [
          957.5838926174497,
          400.0
        ],
        [
          964.1610738255033,
          397.4496644295302
        ],
        [
          966.7114093959731,
          391.9463087248322
        ],
        [
          967.6510067114094,
          382.68456375838923
        ],
        [
          965.7718120805368,
          377.3154362416107
        ],
        [
          962.4161073825503,
          374.76510067114094
        ]
      ],
      "group_id": null,
      "description": "",
      "shape_type": "polygon",
      "flags": {}
    }
  ],
  "imagePath": "00050.jpg",
  "imageHeight": 800,
  "imageWidth": 1360
}