{
  "version": "5.3.1",
  "flags": {},
  "shapes": [
    {
      "label": "prohibitory",
      "points": [
        [
          1223.7,
          419.8
        ],
        [
          1230.7,
          420.3
        ],
        [
          1239.3,
          425.1
        ],
        [
          1242.0,
          432.1
        ],
        [
          1242.5,
          440.1
        ],
        [
          1239.5,
          447.1
        ],
        [
          1233.7,
          451.0
        ],
        [
          1223.8,
          450.6
        ],
        [
          1216.6,
          447.0
        ],
        [
          1214.1,
          439.1
        ],
        [
          1214.6,
          429.3
        ],
        [
          1217.9,
          424.0
        ]
      ],
      "group_id": null,
      "description": "",
      "shape_type": "polygon",
      "flags": {}
    }
  ],
  "imagePath": "00249.jpg",
  "imageHeight": 800,
  "imageWidth": 1360
}