{
  "version": "5.3.1",
  "flags": {},
  "shapes": [
    {
      "label": "other",
      "points": [
        [
          1137.4766355140187,
          328.97196261682245
        ],
        [
          1154.2990654205607,
          327.10280373831773
        ],
        [
          1166.448598130841,
          341.1214953271028
        ],
        [
          1167.3831775700935,
          356.0747663551402
        ],
        [
          1166.448598130841,
          365.42056074766356
        ],
        [
          1149.626168224299,
          372.8971962616822
        ],
        [
          1133.7383177570093,
          371.02803738317755
        ],
        [
          1121.5887850467288,
          361.6822429906542
        ],
        [
          1120.6542056074766,
          344.85981308411215
        ],
        [
          1122.5233644859813,
          333.6448598130841
        ]
      ],
      "group_id": null,
      "description": "",
      "shape_type": "polygon",
      "flags": {}
    }
  ],
  "imagePath": "00302.jpg",
  "imageHeight": 800,
  "imageWidth": 1360
}